{"viewers":[{"id":0,"username":"fadamus","karma":100,"coins":112044},{"id":1,"username":"astrogamer26","karma":100,"coins":171252},{"id":2,"username":"frozendael","karma":140,"coins":147735},{"id":3,"username":"lenzarng","karma":420,"coins":819631},{"id":4,"username":"lenzarbot","karma":420,"coins":215798949},{"id":5,"username":"greggo1410","karma":100,"coins":101306},{"id":6,"username":"onehighzergling","karma":420,"coins":114542},{"id":7,"username":"sushicatyum","karma":140,"coins":166603},{"id":8,"username":"lildyla","karma":100,"coins":46873},{"id":9,"username":"thealangator","karma":100,"coins":20288},{"id":10,"username":"byrds_da_word","karma":100,"coins":62994},{"id":11,"username":"hildunn","karma":100,"coins":44627},{"id":12,"username":"mrben_gaming","karma":420,"coins":238042},{"id":13,"username":"benderisgreat_34_","karma":140,"coins":180537},{"id":14,"username":"tahoedragons","karma":100,"coins":31328},{"id":15,"username":"treecle","karma":100,"coins":62282},{"id":16,"username":"drthtater","karma":100,"coins":6875},{"id":17,"username":"itsberrymore","karma":100,"coins":25750},{"id":18,"username":"leutiankane","karma":420,"coins":208499},{"id":19,"username":"buriastv","karma":100,"coins":83254},{"id":20,"username":"seve82","karma":420,"coins":56857},{"id":21,"username":"elusivesmoke","karma":100,"coins":32858},{"id":22,"username":"mouse5252","karma":420,"coins":339959},{"id":23,"username":"daggoth03","karma":273,"coins":711103},{"id":24,"username":"thrall__owen","karma":100,"coins":77629},{"id":25,"username":"woifmaiden","karma":100,"coins":121915},{"id":26,"username":"littlemsbink","karma":100,"coins":25900},{"id":27,"username":"rygger_dracora","karma":420,"coins":89110},{"id":28,"username":"seasaltheking","karma":100,"coins":2000},{"id":29,"username":"naurisio","karma":100,"coins":1500},{"id":30,"username":"meji","karma":100,"coins":1500},{"id":31,"username":"xv_finchy_vx","karma":100,"coins":2000},{"id":32,"username":"topkazuma","karma":100,"coins":22771},{"id":33,"username":"itsmevivvy","karma":100,"coins":30273},{"id":34,"username":"trunksk","karma":100,"coins":107454},{"id":35,"username":"uthanatos","karma":100,"coins":943},{"id":36,"username":"dimitrions","karma":265,"coins":427901},{"id":37,"username":"poor_furry_justin_darling","karma":100,"coins":6400},{"id":38,"username":"snake_and_guntv","karma":100,"coins":5402},{"id":39,"username":"rando303","karma":100,"coins":99714},{"id":40,"username":"kgu111","karma":420,"coins":85040},{"id":41,"username":"kaliyuuu","karma":100,"coins":15740},{"id":42,"username":"spacecasejlp","karma":100,"coins":98585},{"id":43,"username":"benbratwurst","karma":149,"coins":140128},{"id":44,"username":"costa_18_","karma":100,"coins":20500},{"id":45,"username":"johnryder1","karma":100,"coins":109045},{"id":46,"username":"tova_nator","karma":100,"coins":151410},{"id":47,"username":"hopeful_destroyer","karma":200,"coins":42941},{"id":48,"username":"stephenmutke","karma":100,"coins":20320},{"id":49,"username":"bradusavge","karma":420,"coins":308475},{"id":50,"username":"tryphen1985","karma":100,"coins":5500},{"id":51,"username":"gobrinsan","karma":100,"coins":30002},{"id":52,"username":"thalionrog","karma":100,"coins":3750},{"id":53,"username":"walkin_here","karma":100,"coins":1000},{"id":54,"username":"eveygreenbottle","karma":100,"coins":4250},{"id":55,"username":"ayrtonalexis","karma":100,"coins":7333},{"id":56,"username":"insectuality","karma":100,"coins":1875},{"id":57,"username":"sikee_atric","karma":100,"coins":14343},{"id":58,"username":"dirkdaggershank","karma":100,"coins":100143},{"id":59,"username":"tomthedummy","karma":100,"coins":11142},{"id":60,"username":"prophetn9ne_ix","karma":100,"coins":13500},{"id":61,"username":"milli_milkers","karma":100,"coins":6250},{"id":62,"username":"whitetigger007","karma":100,"coins":12576},{"id":63,"username":"rootbeernole","karma":100,"coins":11487},{"id":64,"username":"solclovser","karma":100,"coins":10805},{"id":65,"username":"ladyelowyn","karma":100,"coins":1000},{"id":66,"username":"namaria1","karma":100,"coins":6375},{"id":67,"username":"dire_prism","karma":100,"coins":13944},{"id":68,"username":"mr_bob_bobington","karma":100,"coins":10342},{"id":69,"username":"julia_mae1230","karma":100,"coins":14095},{"id":70,"username":"thkya","karma":100,"coins":9984},{"id":71,"username":"martinkart8","karma":100,"coins":38520},{"id":72,"username":"wastelandpuppytv","karma":100,"coins":4375},{"id":73,"username":"ninjasteen","karma":100,"coins":16904},{"id":74,"username":"mgabriel2","karma":100,"coins":47375},{"id":75,"username":"chillgreenbean","karma":420,"coins":29105},{"id":76,"username":"firelordizzai","karma":100,"coins":136225},{"id":77,"username":"dhruv_619","karma":100,"coins":73284},{"id":78,"username":"robbysmokez","karma":100,"coins":45912},{"id":79,"username":"theblackzzz","karma":100,"coins":26338},{"id":80,"username":"edvinukes1","karma":420,"coins":34915},{"id":81,"username":"nitriumpower","karma":100,"coins":500},{"id":82,"username":"helloiammurk","karma":100,"coins":33468},{"id":83,"username":"gjbonkers","karma":100,"coins":9313},{"id":84,"username":"derester","karma":100,"coins":11854},{"id":85,"username":"fundedproton","karma":100,"coins":12343},{"id":86,"username":"peachyt82","karma":420,"coins":22909},{"id":87,"username":"team_hope_mikaelson","karma":100,"coins":11843},{"id":88,"username":"pointyy","karma":100,"coins":22892},{"id":89,"username":"mightiemouse","karma":100,"coins":21988},{"id":90,"username":"marcellus_brandt","karma":100,"coins":3250},{"id":91,"username":"defidriume","karma":140,"coins":285206},{"id":92,"username":"yagerhammerhand","karma":100,"coins":26761},{"id":93,"username":"tsupro4you","karma":100,"coins":62155},{"id":94,"username":"xrisu97","karma":100,"coins":204204},{"id":95,"username":"mwahmwanmwah","karma":100,"coins":178051},{"id":96,"username":"berenburgg","karma":100,"coins":16878},{"id":97,"username":"rarepickle2287","karma":100,"coins":39478},{"id":98,"username":"thelogisticschief","karma":100,"coins":70216},{"id":99,"username":"codesagedmc","karma":100,"coins":25405},{"id":100,"username":"1trickpwnyta","karma":100,"coins":15155},{"id":101,"username":"235th_division","karma":100,"coins":1000},{"id":102,"username":"suitald","karma":140,"coins":135761},{"id":103,"username":"lilliedark","karma":100,"coins":10513},{"id":104,"username":"armpit_lover","karma":100,"coins":10327},{"id":105,"username":"weregoat1965","karma":100,"coins":20534},{"id":106,"username":"kitten_lee","karma":100,"coins":4500},{"id":107,"username":"dawntherealmjumper","karma":100,"coins":4375},{"id":108,"username":"ballnutcracker","karma":100,"coins":14551},{"id":109,"username":"dukehugo","karma":100,"coins":140581},{"id":110,"username":"0fallenangelgg0","karma":100,"coins":124425},{"id":111,"username":"marius_samoila","karma":100,"coins":1000},{"id":112,"username":"madreofdragonz7","karma":100,"coins":8500},{"id":113,"username":"tfarksquared","karma":100,"coins":16387},{"id":114,"username":"thezeppster123","karma":100,"coins":1596},{"id":115,"username":"patryk13094","karma":100,"coins":25160},{"id":116,"username":"professionalheckler","karma":100,"coins":14975},{"id":117,"username":"mjw300tv","karma":100,"coins":62918},{"id":118,"username":"evildrewd","karma":100,"coins":13457},{"id":119,"username":"shadowysonz","karma":100,"coins":115644},{"id":120,"username":"professionmksman","karma":420,"coins":394311},{"id":121,"username":"embersof1stdynasty","karma":100,"coins":3943},{"id":122,"username":"johnsn0uu","karma":100,"coins":105648},{"id":123,"username":"the_jazu","karma":100,"coins":11401},{"id":124,"username":"ickyneko","karma":100,"coins":83514},{"id":125,"username":"alexandrakk1","karma":100,"coins":17881},{"id":126,"username":"ps_t4","karma":100,"coins":26770},{"id":127,"username":"zhonghuivad","karma":100,"coins":8391},{"id":128,"username":"thetrippleadam","karma":100,"coins":13752},{"id":129,"username":"jhargrimm","karma":100,"coins":1500},{"id":130,"username":"vandellyr","karma":100,"coins":25633},{"id":131,"username":"tustarwarsguy94","karma":100,"coins":4500},{"id":132,"username":"talamar1","karma":420,"coins":235196},{"id":133,"username":"itsmevivy","karma":100,"coins":109664},{"id":134,"username":"geleph","karma":100,"coins":20155},{"id":135,"username":"yourewolch","karma":100,"coins":99890},{"id":136,"username":"geirrodur","karma":100,"coins":30062},{"id":137,"username":"nethercloud","karma":100,"coins":8981},{"id":138,"username":"fjarie","karma":100,"coins":875},{"id":139,"username":"chriswiththerizzz","karma":100,"coins":3875},{"id":140,"username":"somethinghumble","karma":100,"coins":1375},{"id":141,"username":"lilmia_casand","karma":420,"coins":338639},{"id":142,"username":"genialstarter","karma":100,"coins":2375},{"id":143,"username":"tutugamoficial","karma":100,"coins":10138},{"id":144,"username":"koder00","karma":100,"coins":17537},{"id":145,"username":"unhingedlime","karma":100,"coins":7125},{"id":146,"username":"dragoncrygames","karma":100,"coins":114108},{"id":147,"username":"dukewhisky","karma":100,"coins":77209},{"id":148,"username":"thrillingsymbolism","karma":100,"coins":5500},{"id":149,"username":"dragonsbreath9","karma":100,"coins":4250},{"id":150,"username":"thicciest_burrito","karma":100,"coins":202922},{"id":151,"username":"sildabirb","karma":100,"coins":84230},{"id":152,"username":"shinyyorik","karma":100,"coins":8000},{"id":153,"username":"peskyfox97","karma":100,"coins":19592},{"id":154,"username":"knightofthegarden","karma":100,"coins":8000},{"id":155,"username":"t1ltedgaming","karma":100,"coins":1000},{"id":156,"username":"qt_wasp","karma":100,"coins":8000},{"id":157,"username":"cozymwah","karma":100,"coins":53422},{"id":158,"username":"alex1cey","karma":100,"coins":4875},{"id":159,"username":"ohwikked","karma":100,"coins":30255},{"id":160,"username":"knightowl925","karma":100,"coins":1500},{"id":161,"username":"ashomir","karma":100,"coins":9763},{"id":162,"username":"efzapa","karma":100,"coins":7750},{"id":163,"username":"mavismoonlight","karma":100,"coins":1000},{"id":164,"username":"anttyrant","karma":100,"coins":12279},{"id":165,"username":"tremoir","karma":100,"coins":1500},{"id":166,"username":"ke0ki_gnok","karma":100,"coins":1500},{"id":167,"username":"anke1326","karma":100,"coins":1500},{"id":168,"username":"emceeemazing","karma":100,"coins":1500},{"id":169,"username":"hackerhasuracc","karma":100,"coins":1000},{"id":170,"username":"darkguacshrimp","karma":100,"coins":13577},{"id":171,"username":"meoweedek","karma":100,"coins":4000},{"id":172,"username":"thespeedofkurt","karma":100,"coins":7841},{"id":173,"username":"silkytopcoat","karma":100,"coins":4375},{"id":174,"username":"dantastic2022","karma":100,"coins":114331},{"id":175,"username":"no_lives_left_","karma":100,"coins":192057},{"id":176,"username":"pincheddiary","karma":100,"coins":500},{"id":177,"username":"thefmdaddy","karma":100,"coins":1375},{"id":178,"username":"hosam_0123","karma":100,"coins":12530},{"id":179,"username":"imlovingit66","karma":100,"coins":14026},{"id":180,"username":"flziy","karma":100,"coins":10267},{"id":181,"username":"alejoyt11lan1","karma":100,"coins":3375},{"id":182,"username":"horsekel06","karma":100,"coins":2875},{"id":183,"username":"fabulich","karma":100,"coins":3375},{"id":184,"username":"souza0206","karma":100,"coins":11843},{"id":185,"username":"reignsupreme_o7","karma":100,"coins":70252},{"id":186,"username":"tlacnov24","karma":140,"coins":6980},{"id":187,"username":"queensombra","karma":100,"coins":15845},{"id":188,"username":"soundalerts","karma":100,"coins":60975},{"id":189,"username":"mouseygloom","karma":100,"coins":9559},{"id":190,"username":"exeore21","karma":100,"coins":111617},{"id":191,"username":"bigtreehappy","karma":100,"coins":11649},{"id":192,"username":"dominicook","karma":420,"coins":120344},{"id":193,"username":"draculajr","karma":100,"coins":3875},{"id":194,"username":"clandestinepogromp3","karma":100,"coins":6000},{"id":195,"username":"themike121","karma":100,"coins":11413},{"id":196,"username":"aramati","karma":100,"coins":1500},{"id":197,"username":"streamlabs","karma":100,"coins":1540},{"id":198,"username":"destructive_goose","karma":100,"coins":18093},{"id":199,"username":"manicuredeaterfl","karma":100,"coins":500},{"id":200,"username":"pgoham","karma":100,"coins":10330},{"id":201,"username":"yurician1","karma":420,"coins":215269},{"id":202,"username":"exreveng3r","karma":100,"coins":22994},{"id":203,"username":"kristianiastorm","karma":100,"coins":9607},{"id":204,"username":"gamingantboi","karma":100,"coins":865},{"id":205,"username":"halfwayteddyfsqev","karma":100,"coins":7200},{"id":206,"username":"rylieliana76","karma":100,"coins":8000},{"id":207,"username":"sierrastrawbeary","karma":100,"coins":8911},{"id":208,"username":"daceia","karma":100,"coins":9644},{"id":209,"username":"littlebattousai","karma":200,"coins":8669},{"id":210,"username":"always_smile_0","karma":100,"coins":9000},{"id":211,"username":"big_oossshh","karma":100,"coins":6400},{"id":212,"username":"ratbeegee","karma":100,"coins":22250},{"id":213,"username":"jnscrkdfngr","karma":100,"coins":6198087},{"id":214,"username":"koester","karma":100,"coins":13675},{"id":215,"username":"mellowwhispersss","karma":420,"coins":98225},{"id":216,"username":"flyingscotsmanchris","karma":100,"coins":27470},{"id":217,"username":"jerkyhomelandaedszjksh83y","karma":100,"coins":27220},{"id":218,"username":"chuckplays","karma":100,"coins":24845},{"id":219,"username":"axolozzl","karma":100,"coins":24845},{"id":220,"username":"tweenykilla","karma":420,"coins":89951},{"id":221,"username":"profdrhamster","karma":100,"coins":15345},{"id":222,"username":"cheddarfishhh","karma":100,"coins":24470},{"id":223,"username":"kingmoo92","karma":100,"coins":14875},{"id":224,"username":"manfredvondarling","karma":100,"coins":17158},{"id":225,"username":"xxirs17ixx","karma":100,"coins":15000},{"id":226,"username":"canceitv","karma":420,"coins":43529},{"id":227,"username":"3mpr355","karma":100,"coins":61592},{"id":228,"username":"acoolguy4ever","karma":420,"coins":37537},{"id":229,"username":"earless_trout","karma":100,"coins":10125},{"id":230,"username":"djsmoochum","karma":420,"coins":78560},{"id":231,"username":"its_sam86","karma":100,"coins":34025},{"id":232,"username":"drudiki","karma":100,"coins":3000},{"id":233,"username":"sakurated","karma":100,"coins":9125},{"id":234,"username":"maidenmasquerade","karma":100,"coins":9875},{"id":235,"username":"sunny__","karma":100,"coins":18204},{"id":236,"username":"arviu90","karma":100,"coins":9475},{"id":237,"username":"bonkihart","karma":100,"coins":47666},{"id":238,"username":"hektikrebel","karma":100,"coins":18884},{"id":239,"username":"kaoslobster","karma":100,"coins":16636},{"id":240,"username":"si0301","karma":100,"coins":10375},{"id":241,"username":"leetownage420","karma":420,"coins":40630},{"id":242,"username":"domxx9","karma":140,"coins":13918},{"id":243,"username":"iya_ilene","karma":100,"coins":10375},{"id":244,"username":"unholydmc","karma":140,"coins":38905},{"id":245,"username":"tineck","karma":100,"coins":20700},{"id":246,"username":"pennerr_100","karma":100,"coins":20250},{"id":247,"username":"softblanketsnuggels","karma":100,"coins":147100},{"id":248,"username":"boaluigi","karma":100,"coins":12780},{"id":249,"username":"kafvus","karma":420,"coins":1184736},{"id":250,"username":"xhollowworld","karma":100,"coins":6050},{"id":251,"username":"thecoffeecolonist","karma":420,"coins":6434},{"id":252,"username":"shadows_assassin","karma":100,"coins":9220},{"id":253,"username":"zzdrzeuszz","karma":100,"coins":1700},{"id":254,"username":"tumbleweed_official","karma":100,"coins":7100},{"id":255,"username":"neozemis42","karma":100,"coins":5650},{"id":256,"username":"neozemis42","karma":100,"coins":5650},{"id":257,"username":"old_red_fox_","karma":100,"coins":4850},{"id":258,"username":"old_red_fox_","karma":100,"coins":4850},{"id":259,"username":"inordinatenubbxeg","karma":100,"coins":9850},{"id":260,"username":"inordinatenubbxeg","karma":100,"coins":9850},{"id":261,"username":"rusty_hammerhead","karma":100,"coins":8250},{"id":262,"username":"rusty_hammerhead","karma":100,"coins":8250},{"id":263,"username":"darkfoldgames","karma":100,"coins":3450},{"id":264,"username":"darkfoldgames","karma":100,"coins":3450},{"id":265,"username":"captolamia","karma":100,"coins":7350},{"id":266,"username":"captolamia","karma":100,"coins":7350},{"id":267,"username":"angeltera01","karma":100,"coins":7050},{"id":268,"username":"angeltera01","karma":100,"coins":7050},{"id":269,"username":"dame_kira_mumpitz","karma":100,"coins":3650},{"id":270,"username":"dame_kira_mumpitz","karma":100,"coins":3650},{"id":271,"username":"nicky00009","karma":100,"coins":3450},{"id":272,"username":"nicky00009","karma":100,"coins":3450},{"id":273,"username":"doinforever","karma":100,"coins":4950},{"id":274,"username":"doinforever","karma":100,"coins":4950},{"id":275,"username":"lurking_doc","karma":100,"coins":2450},{"id":276,"username":"lurking_doc","karma":100,"coins":2450},{"id":277,"username":"tinysnowflake","karma":100,"coins":3899},{"id":278,"username":"tinysnowflake","karma":100,"coins":3899},{"id":279,"username":"waisuru","karma":100,"coins":2250},{"id":280,"username":"waisuru","karma":100,"coins":2250}],"total":281}